synten/__init__.py
synten/clusters.py
synten/decomposition_generator.py
synten/experiment_runner.py
synten/images.py
synten/networks.py
synten/timeseries.py
synten-0.0.1.dist-info/LICENSE
synten-0.0.1.dist-info/METADATA
synten-0.0.1.dist-info/WHEEL
synten-0.0.1.dist-info/top_level.txt
synten-0.0.1.dist-info/RECORD
