Metadata-Version: 2.1
Name: synten
Version: 0.0.1
Summary: UNKNOWN
Home-page: UNKNOWN
Author: Marie Roald
Author-email: UNKNOWN
License: UNKNOWN
Platform: UNKNOWN
Requires-Dist: numpy
Requires-Dist: scikit-learn
Requires-Dist: subclass-register
Requires-Dist: tensorkit
Requires-Dist: tensorkit-tools
